pytest_recordings/__init__.py
pytest_recordings/decorators/request_logging.py
pytest_recordings/hooks.py
pytest_recordings/screenshot.py
pytest_recordings-0.4.2.dist-info/entry_points.txt
pytest_recordings-0.4.2.dist-info/WHEEL
pytest_recordings-0.4.2.dist-info/METADATA
pytest_recordings-0.4.2.dist-info/RECORD
